lit_data_layers/__init__.py
lit_data_layers/sqldb/__init__.py
lit_data_layers/sqldb/models.py
lit_data_layers-0.1.4.dist-info/LICENSE
lit_data_layers-0.1.4.dist-info/METADATA
lit_data_layers-0.1.4.dist-info/WHEEL
lit_data_layers-0.1.4.dist-info/RECORD
