Metadata-Version: 2.1
Name: lit-data-layers
Version: 0.1.4
Summary: A collection of data layers for Chainlit, persist state on your own infrastructure!
Author: Aniruddha Adhikary
Requires-Python: >=3.10,<4.0
Classifier: Programming Language :: Python :: 3
Classifier: Programming Language :: Python :: 3.10
Classifier: Programming Language :: Python :: 3.11
Classifier: Programming Language :: Python :: 3.12
Provides-Extra: postgres
Provides-Extra: sqlite
Requires-Dist: aiosqlite (>=0.20.0,<0.21.0) ; extra == "sqlite"
Requires-Dist: asyncpg (>=0.29.0,<0.30.0) ; extra == "postgres"
Requires-Dist: chainlit (>=1.0.401,<2.0.0)
Requires-Dist: sqlalchemy[asyncio] (>=2.0.29,<3.0.0) ; extra == "postgres" or extra == "sqlite"
